MANIFEST.in
README.md
noeq.py
setup.py
noeq.egg-info/PKG-INFO
noeq.egg-info/SOURCES.txt
noeq.egg-info/dependency_links.txt
noeq.egg-info/top_level.txt