Metadata-Version: 1.0
Name: noeq
Version: 1.0
Summary: Noeq client
Home-page: https://github.com/noeq/python-noeq
Author: Chris Petersen
Author-email: geek@ex-nerd.com
License: MIT
Platform: UNKNOWN
Classifier: Development Status :: 5 - Production/Stable
Classifier: Environment :: Web Environment
Classifier: Intended Audience :: Developers
Classifier: License :: OSI Approved :: MIT License
Classifier: Operating System :: OS Independent
Classifier: Programming Language :: Python
Classifier: Topic :: Utilities
